{
  "小学生向けの雑学クイズ": [
    {
      "question": "日本で一番高い山は？",
      "options": [
        "北岳",
        "富士山",
        "南アルプス",
        "八ヶ岳"
      ],
      "correct": 1
    },
    {
      "question": "太陽が上る方向は？",
      "options": [
        "西",
        "南",
        "東",
        "北"
      ],
      "correct": 2
    },
    {
      "question": "1年は何日？",
      "options": [
        "365日",
        "360日",
        "370日",
        "350日"
      ],
      "correct": 0
    },
    {
      "question": "世界で一番大きい大陸は？",
      "options": [
        "アフリカ大陸",
        "アジア大陸",
        "南米大陸",
        "北米大陸"
      ],
      "correct": 1
    },
    {
      "question": "ペンギンはどこに住んでいる？",
      "options": [
        "北極",
        "赤道付近",
        "南極",
        "砂漠"
      ],
      "correct": 2
    },
    {
      "question": "クジラの大きさで一番大きいのは？",
      "options": [
        "ザトウクジラ",
        "マッコウクジラ",
        "シロナガスクジラ",
        "イッカク"
      ],
      "correct": 2
    },
    {
      "question": "地球の表面のほとんどは？",
      "options": [
        "砂漠",
        "森",
        "水",
        "山"
      ],
      "correct": 2
    },
    {
      "question": "虹は何の色でできている？",
      "options": [
        "赤・青・緑",
        "赤・橙・黄・緑・青・藍・紫",
        "赤・黄・青",
        "白と黒"
      ],
      "correct": 1
    },
    {
      "question": "人間が1日に飲む水はどれくらい？",
      "options": [
        "1リットル",
        "2リットル",
        "5リットル",
        "10リットル"
      ],
      "correct": 1
    },
    {
      "question": "電球を発明したのは？",
      "options": [
        "ニュートン",
        "エジソン",
        "ダ・ヴィンチ",
        "ファラデー"
      ],
      "correct": 1
    },
    {
      "question": "蜂蜜を作るのは？",
      "options": [
        "トンボ",
        "ミツバチ",
        "テントウムシ",
        "アリ"
      ],
      "correct": 1
    },
    {
      "question": "象の歯は何本？",
      "options": [
        "20本",
        "30本",
        "40本",
        "50本以上"
      ],
      "correct": 2
    },
    {
      "question": "人間の骨は何本？",
      "options": [
        "150本",
        "206本",
        "300本",
        "400本"
      ],
      "correct": 1
    },
    {
      "question": "ダイヤモンドは何からできている？",
      "options": [
        "砂",
        "氷",
        "炭素",
        "塩"
      ],
      "correct": 2
    },
    {
      "question": "バナナの皮が黄色くなるのは？",
      "options": [
        "日に当たると",
        "熟れると",
        "雨が当たると",
        "風が吹くと"
      ],
      "correct": 1
    },
    {
      "question": "カカオはどの国が原産地？",
      "options": [
        "日本",
        "アフリカ",
        "南米",
        "オーストラリア"
      ],
      "correct": 2
    },
    {
      "question": "チーズはどうやって作る？",
      "options": [
        "牛乳を冷やす",
        "牛乳を固める",
        "牛乳にクリームを混ぜる",
        "牛乳を塩漬けにする"
      ],
      "correct": 1
    },
    {
      "question": "パンダが1日に食べる竹は？",
      "options": [
        "1kg",
        "5kg",
        "10kg以上",
        "100kg"
      ],
      "correct": 2
    },
    {
      "question": "キリンの首の骨は何個？",
      "options": [
        "7個",
        "15個",
        "20個",
        "50個以上"
      ],
      "correct": 0
    },
    {
      "question": "蜘蛛の足は何本？",
      "options": [
        "4本",
        "6本",
        "8本",
        "10本"
      ],
      "correct": 2
    },
    {
      "question": "星はなぜ点滅して見える？",
      "options": [
        "実は動いている",
        "大気の影響で",
        "壊れかけている",
        "昼と夜で見え方が変わる"
      ],
      "correct": 1
    },
    {
      "question": "月はどのくらいで地球を1周する？",
      "options": [
        "1日",
        "1週間",
        "1ヶ月",
        "1年"
      ],
      "correct": 2
    },
    {
      "question": "雲はなぜ空に浮いている？",
      "options": [
        "誰かが持っている",
        "水の粒が軽いから",
        "風に押されているから",
        "魔法で"
      ],
      "correct": 2
    },
    {
      "question": "雪が白いのは？",
      "options": [
        "氷が白いから",
        "小さな氷の粒の間に空気があるから",
        "塩が入っているから",
        "光を反射しないから"
      ],
      "correct": 1
    },
    {
      "question": "風はなぜ吹く？",
      "options": [
        "誰かが吹いている",
        "気温の差で空気が動く",
        "木が揺れるから",
        "ランダムに起こる"
      ],
      "correct": 1
    },
    {
      "question": "渡り鳥はなぜ渡る？",
      "options": [
        "つまらないから",
        "食べ物や温度を求めて",
        "遊ぶために",
        "訓練のために"
      ],
      "correct": 1
    },
    {
      "question": "魚はなぜ眠そうに見える？",
      "options": [
        "本当に寝ている",
        "目を閉じないから",
        "いつも同じ顔だから",
        "動きが遅いから"
      ],
      "correct": 2
    },
    {
      "question": "サボテンはなぜ針がある？",
      "options": [
        "敵から身を守る",
        "水を集めるため",
        "動物に食べられないため",
        "全部あっている"
      ],
      "correct": 3
    },
    {
      "question": "トマトが赤いのはなぜ？",
      "options": [
        "栄養",
        "赤い色の成分が含まれているから",
        "日に当たっているから",
        "毒だから"
      ],
      "correct": 1
    },
    {
      "question": "人間の心臓は1分間に何回動く？",
      "options": [
        "30回",
        "60～80回",
        "150回",
        "300回"
      ],
      "correct": 1
    },
    {
      "question": "爪はなぜ伸び続ける？",
      "options": [
        "栄養をため込むから",
        "古い細胞が押し出されるから",
        "骨の一部だから",
        "生え変わるから"
      ],
      "correct": 1
    },
    {
      "question": "あくびはなぜうつる？",
      "options": [
        "病気だから",
        "リラックスしているから",
        "脳の同調作用",
        "眠いから"
      ],
      "correct": 2
    },
    {
      "question": "毛はなぜ生える？",
      "options": [
        "体を暖める",
        "体を守る",
        "感覚を得る",
        "全部あっている"
      ],
      "correct": 3
    },
    {
      "question": "涙はなぜ出る？",
      "options": [
        "目を潤す",
        "悲しいとき",
        "ストレス対策",
        "全部あっている"
      ],
      "correct": 3
    },
    {
      "question": "くしゃみはなぜ出る？",
      "options": [
        "汚れを吹き飛ばす",
        "健康な証",
        "反射的に",
        "風邪だから"
      ],
      "correct": 0
    },
    {
      "question": "お腹が鳴るのはなぜ？",
      "options": [
        "臓器が動いているから",
        "ガスが動くから",
        "筋肉が収縮するから",
        "信号が送られてるから"
      ],
      "correct": 2
    },
    {
      "question": "舌の下にある玉は何？",
      "options": [
        "唾液腺",
        "筋肉",
        "骨",
        "リンパ節"
      ],
      "correct": 0
    },
    {
      "question": "アルプスはどこにある？",
      "options": [
        "南米",
        "オーストラリア",
        "ヨーロッパ",
        "アメリカ"
      ],
      "correct": 2
    },
    {
      "question": "ナイル川はどこの国を流れている？",
      "options": [
        "フランス",
        "ブラジル",
        "エジプト",
        "インド"
      ],
      "correct": 2
    },
    {
      "question": "ピラミッドはどこにある？",
      "options": [
        "インカ帝国",
        "エジプト",
        "メキシコ",
        "イスラエル"
      ],
      "correct": 1
    },
    {
      "question": "自由の女神はどこにある？",
      "options": [
        "フランス",
        "イギリス",
        "アメリカ",
        "カナダ"
      ],
      "correct": 2
    },
    {
      "question": "万里の長城はどこにある？",
      "options": [
        "日本",
        "韓国",
        "中国",
        "モンゴル"
      ],
      "correct": 2
    },
    {
      "question": "サハラ砂漠はどこにある？",
      "options": [
        "中東",
        "アフリカ",
        "オーストラリア",
        "南米"
      ],
      "correct": 1
    },
    {
      "question": "パリはどこの国の首都？",
      "options": [
        "イギリス",
        "フランス",
        "ドイツ",
        "イタリア"
      ],
      "correct": 1
    },
    {
      "question": "東京はどこにある？",
      "options": [
        "関西",
        "関東",
        "九州",
        "北海道"
      ],
      "correct": 1
    },
    {
      "question": "お正月に飾られる花は？",
      "options": [
        "チューリップ",
        "薔薇",
        "門松と松",
        "ひまわり"
      ],
      "correct": 2
    },
    {
      "question": "七夕はいつ？",
      "options": [
        "1月1日",
        "7月7日",
        "12月25日",
        "11月3日"
      ],
      "correct": 1
    },
    {
      "question": "お正月に食べるお餅はなぜ食べる？",
      "options": [
        "おいしいから",
        "健康になるから",
        "新しい年の幸せを祈るから",
        "家族の行事だから"
      ],
      "correct": 2
    },
    {
      "question": "ひな祭りはいつ？",
      "options": [
        "1月3日",
        "3月3日",
        "5月5日",
        "9月9日"
      ],
      "correct": 1
    },
    {
      "question": "こどもの日はいつ？",
      "options": [
        "3月3日",
        "4月1日",
        "5月5日",
        "6月1日"
      ],
      "correct": 2
    },
    {
      "question": "七五三はいつする？",
      "options": [
        "春",
        "夏",
        "秋",
        "冬"
      ],
      "correct": 2
    },
    {
      "question": "お盆はいつ？",
      "options": [
        "7月中旬～8月中旬",
        "1月1日～3日",
        "12月25日",
        "3月中旬"
      ],
      "correct": 0
    },
    {
      "question": "サンタクロースはいつ現れる？",
      "options": [
        "1月1日",
        "12月25日",
        "12月24日夜",
        "11月1日"
      ],
      "correct": 2
    },
    {
      "question": "バレンタインデーは何をする日？",
      "options": [
        "誕生日を祝う",
        "愛を伝える",
        "友情を祝う",
        "新しい年を祝う"
      ],
      "correct": 1
    },
    {
      "question": "ホワイトデーはいつ？",
      "options": [
        "1月14日",
        "2月14日",
        "3月14日",
        "4月14日"
      ],
      "correct": 2
    },
    {
      "question": "野球の1試合は何イニング？",
      "options": [
        "3イニング",
        "6イニング",
        "9イニング",
        "12イニング"
      ],
      "correct": 2
    },
    {
      "question": "サッカーのコートの長さは？",
      "options": [
        "50～80m",
        "100～120m",
        "100～130m",
        "150～170m"
      ],
      "correct": 2
    },
    {
      "question": "バスケットボールのコートの高さは？",
      "options": [
        "2m",
        "2.5m",
        "3m",
        "3.5m"
      ],
      "correct": 2
    },
    {
      "question": "テニスの試合で勝つために必要なセット数は？",
      "options": [
        "1セット",
        "2セット",
        "3セット",
        "4セット"
      ],
      "correct": 2
    },
    {
      "question": "オリンピックは何年ごとに開かれる？",
      "options": [
        "1年",
        "2年",
        "4年",
        "8年"
      ],
      "correct": 2
    },
    {
      "question": "ワールドカップは何年ごと？",
      "options": [
        "2年",
        "3年",
        "4年",
        "5年"
      ],
      "correct": 2
    },
    {
      "question": "ボクシングでノックアウトと判定されるまでの秒数は？",
      "options": [
        "3秒",
        "5秒",
        "10秒",
        "15秒"
      ],
      "correct": 2
    },
    {
      "question": "柔道の帯の色で一番初心者用は？",
      "options": [
        "白",
        "黄",
        "茶",
        "黒"
      ],
      "correct": 0
    },
    {
      "question": "剣道の竹刀を打つ部位は？",
      "options": [
        "手",
        "足",
        "頭",
        "全部"
      ],
      "correct": 3
    },
    {
      "question": "ハンマー投げはどのくらい投げる？",
      "options": [
        "30m",
        "50m",
        "70m以上",
        "100m以上"
      ],
      "correct": 2
    },
    {
      "question": "陸上短距離走で一番短い距離は？",
      "options": [
        "100m",
        "200m",
        "400m",
        "50m"
      ],
      "correct": 3
    },
    {
      "question": "マラソンの距離は？",
      "options": [
        "10km",
        "21km",
        "42.195km",
        "50km"
      ],
      "correct": 2
    },
    {
      "question": "ウイスキーはどこが発祥？",
      "options": [
        "フランス",
        "日本",
        "スコットランド",
        "アメリカ"
      ],
      "correct": 2
    },
    {
      "question": "寿司はどこの国の料理？",
      "options": [
        "中国",
        "タイ",
        "日本",
        "コリア"
      ],
      "correct": 2
    },
    {
      "question": "ピザはどこが発祥？",
      "options": [
        "アメリカ",
        "フランス",
        "イタリア",
        "スペイン"
      ],
      "correct": 2
    },
    {
      "question": "ハンバーガーの発祥地は？",
      "options": [
        "フランス",
        "ドイツ",
        "アメリカ",
        "イギリス"
      ],
      "correct": 2
    },
    {
      "question": "ラーメンはどこから伝わった？",
      "options": [
        "アメリカ",
        "中国",
        "フランス",
        "タイ"
      ],
      "correct": 1
    },
    {
      "question": "天ぷらはどこが発祥？",
      "options": [
        "中国",
        "ポルトガル",
        "スペイン",
        "フランス"
      ],
      "correct": 1
    },
    {
      "question": "カレーはどこが発祥？",
      "options": [
        "タイ",
        "インド",
        "日本",
        "マレーシア"
      ],
      "correct": 1
    },
    {
      "question": "パスタはどこが発祥？",
      "options": [
        "フランス",
        "スペイン",
        "イタリア",
        "ギリシャ"
      ],
      "correct": 2
    },
    {
      "question": "アイスクリームの原型はどこが発祥？",
      "options": [
        "アメリカ",
        "イタリア",
        "中国",
        "フランス"
      ],
      "correct": 1
    },
    {
      "question": "コーヒーはどこが原産地？",
      "options": [
        "インド",
        "ブラジル",
        "アフリカ（エチオピア）",
        "インドネシア"
      ],
      "correct": 2
    },
    {
      "question": "紙はいつ誰が発明した？",
      "options": [
        "古代中国",
        "古代エジプト",
        "古代ローマ",
        "古代ギリシャ"
      ],
      "correct": 0
    },
    {
      "question": "活字印刷を発明したのは？",
      "options": [
        "グーテンベルク",
        "エジソン",
        "ニュートン",
        "ガリレオ"
      ],
      "correct": 0
    },
    {
      "question": "蒸気機関を改良したのは？",
      "options": [
        "ワット",
        "エジソン",
        "ダ・ヴィンチ",
        "フランクリン"
      ],
      "correct": 0
    },
    {
      "question": "電話を発明したのは？",
      "options": [
        "ベル",
        "エジソン",
        "フランクリン",
        "ワット"
      ],
      "correct": 0
    },
    {
      "question": "原子を発見したのは？",
      "options": [
        "ニュートン",
        "ダルトン",
        "ボーア",
        "アイスシュタイン"
      ],
      "correct": 1
    },
    {
      "question": "【難問】フェルマーの最終定理を解いた数学者は？",
      "options": [
        "ラマヌジャン",
        "ガウス",
        "アンドリュー・ワイルズ",
        "ポアンカレ"
      ],
      "correct": 2
    },
    {
      "question": "ピアノは何本の鍵盤がある？",
      "options": [
        "52鍵",
        "61鍵",
        "88鍵",
        "100鍵"
      ],
      "correct": 2
    },
    {
      "question": "バイオリンは何本の弦がある？",
      "options": [
        "3本",
        "4本",
        "5本",
        "6本"
      ],
      "correct": 1
    },
    {
      "question": "ギターは何本の弦がある？",
      "options": [
        "4本",
        "5本",
        "6本",
        "7本"
      ],
      "correct": 2
    },
    {
      "question": "フルートは何個の穴がある？",
      "options": [
        "3個",
        "6個",
        "9個",
        "12個"
      ],
      "correct": 1
    },
    {
      "question": "【難問】モーツァルトが作曲した交響曲は何曲？",
      "options": [
        "39曲",
        "41曲",
        "50曲",
        "60曲"
      ],
      "correct": 1
    },
    {
      "question": "日本の紙幣で一番高い金額は？",
      "options": [
        "1000円",
        "5000円",
        "10000円",
        "50000円"
      ],
      "correct": 2
    },
    {
      "question": "硬貨で一番高い金額は？",
      "options": [
        "50円",
        "100円",
        "500円",
        "1000円"
      ],
      "correct": 2
    },
    {
      "question": "銀行に預けたお金はどこに保管される？",
      "options": [
        "机の下",
        "金庫",
        "銀行のコンピュータ",
        "複数の場所"
      ],
      "correct": 3
    },
    {
      "question": "株とは？",
      "options": [
        "木の棒",
        "会社の一部を持つ権利",
        "銀行のお金",
        "給料"
      ],
      "correct": 1
    },
    {
      "question": "【難問】ビットコインを作ったサトシ・ナカモトの正体は？",
      "options": [
        "日本人",
        "アメリカ人",
        "不明",
        "AI"
      ],
      "correct": 2
    },
    {
      "question": "保険とは？",
      "options": [
        "銀行",
        "もしもの時のため",
        "投資",
        "給料"
      ],
      "correct": 1
    },
    {
      "question": "税金は何に使われる？",
      "options": [
        "政治家の給料だけ",
        "学校や道路など公共の物",
        "企業のみ",
        "金持ちのみ"
      ],
      "correct": 1
    },
    {
      "question": "パスポートは何のために必要？",
      "options": [
        "バスに乗る",
        "外国に行く",
        "学校に行く",
        "病院に行く"
      ],
      "correct": 1
    },
    {
      "question": "【難問】現在のWHO事務局長は誰か（2024年時点）？",
      "options": [
        "テドロス・アダノム",
        "グテーレス",
        "バッハ",
        "グティエレス"
      ],
      "correct": 0
    },
    {
      "question": "国連の本部はどこにある？",
      "options": [
        "ジュネーブ",
        "ニューヨーク",
        "ロンドン",
        "パリ"
      ],
      "correct": 1
    },
    {
      "question": "アメリカの首都は？",
      "options": [
        "ニューヨーク",
        "ロサンゼルス",
        "ワシントンD.C.",
        "シカゴ"
      ],
      "correct": 2
    },
    {
      "question": "オーストラリアの首都は？",
      "options": [
        "シドニー",
        "メルボルン",
        "キャンベラ",
        "ブリスベン"
      ],
      "correct": 2
    },
    {
      "question": "インドの首都は？",
      "options": [
        "ムンバイ",
        "ニューデリー",
        "バンガロール",
        "チェンナイ"
      ],
      "correct": 1
    }
  ]
}
